LICENSE
MANIFEST.in
README.md
VERSION
requirements.amqp.txt
requirements.db.txt
requirements.redis.txt
requirements.txt
setup.cfg
setup.py
popug_sdk/__init__.py
popug_sdk/application.py
popug_sdk/py.typed
popug_sdk.egg-info/PKG-INFO
popug_sdk.egg-info/SOURCES.txt
popug_sdk.egg-info/dependency_links.txt
popug_sdk.egg-info/not-zip-safe
popug_sdk.egg-info/requires.txt
popug_sdk.egg-info/top_level.txt
popug_sdk/amqp/__init__.py
popug_sdk/amqp/consumer.py
popug_sdk/amqp/events.py
popug_sdk/amqp/producer.py
popug_sdk/amqp/utils.py
popug_sdk/conf/__init__.py
popug_sdk/conf/amqp.py
popug_sdk/conf/constants.py
popug_sdk/conf/db.py
popug_sdk/conf/global_settings.py
popug_sdk/conf/redis.py
popug_sdk/db/__init__.py
popug_sdk/db/base_class.py
popug_sdk/db/registry.py
popug_sdk/management/__init__.py
popug_sdk/management/commands/__init__.py
popug_sdk/management/commands/dbshell.py
popug_sdk/management/commands/init_alembic.py
popug_sdk/management/commands/makemigrations.py
popug_sdk/management/commands/migrate.py
popug_sdk/management/commands/runserver.py
popug_sdk/management/commands/shell.py
popug_sdk/management/commands/test.py
popug_sdk/redis/__init__.py
popug_sdk/redis/context_manager.py
popug_sdk/redis/redis_pool.py
popug_sdk/schemas/__init__.py
popug_sdk/schemas/pong.py