Metadata-Version: 2.1
Name: popug-sdk
Version: 0.0.3
Summary: Package for uber popug training project
Home-page: https://github.com/Drozdetskiy/popug_jira
Author: Mikhail Drozdetskiy
Author-email: m.drozdetskiy.dev@gmail.com
License: UNKNOWN
Platform: UNKNOWN
Provides-Extra: db
Provides-Extra: amqp
Provides-Extra: redis
Provides-Extra: all
License-File: LICENSE
